openla_feature_representation/__init__.py
openla_feature_representation/alp/__init__.py
openla_feature_representation/alp/alp.py
openla_feature_representation/alp/extract_feature_alp.py
openla_feature_representation/alp/features_extracted_function.py
openla_feature_representation/alp/load_dataset.py
openla_feature_representation/alp/utils.py
openla_feature_representation/e2vec/openla_e2vec.py
openla_feature_representation-0.1.3.dist-info/LICENSE
openla_feature_representation-0.1.3.dist-info/METADATA
openla_feature_representation-0.1.3.dist-info/WHEEL
openla_feature_representation-0.1.3.dist-info/RECORD
