Metadata-Version: 2.1
Name: openla-feature-representation
Version: 0.1.3
Summary: A Python module that adds features to OpenLA data to make it easier to use for ML
Author: LIMU
Author-email: repository@limu.ait.kyushu-u.ac.jp
Requires-Python: >=3.8,<4.0
Classifier: Programming Language :: Python :: 3
Classifier: Programming Language :: Python :: 3.8
Classifier: Programming Language :: Python :: 3.9
Classifier: Programming Language :: Python :: 3.10
Classifier: Programming Language :: Python :: 3.11
Classifier: Programming Language :: Python :: 3.12
Requires-Dist: fasttext-wheel (>=0.9.2,<0.10.0)
Requires-Dist: openla (>=0.2.8,<0.3.0)
